faster_hash.so
faster_hash-0.0.4.dist-info/WHEEL
faster_hash-0.0.4.dist-info/top_level.txt
faster_hash-0.0.4.dist-info/METADATA
faster_hash-0.0.4.dist-info/RECORD
