Metadata-Version: 1.1
Name: faster-hash
Version: 0.0.4
Summary: fnv1a in Cython
Home-page: https://github.com/xiachufang/faster-hash
Author: gfreezy
Author-email: gfreezy@gmail.com
License: UNKNOWN
Platform: UNKNOWN
Classifier: Programming Language :: Python :: 2.7
Classifier: Programming Language :: Python :: 3
